MANIFEST.in
requirements.txt
setup.py
aclapiclient/__init__.py
aclapiclient/aclapiclient.py
aclapiclient/job_executor.py
aclapiclient/l4_options.py
python_aclapiclient.egg-info/PKG-INFO
python_aclapiclient.egg-info/SOURCES.txt
python_aclapiclient.egg-info/dependency_links.txt
python_aclapiclient.egg-info/requires.txt
python_aclapiclient.egg-info/top_level.txt