Metadata-Version: 1.1
Name: python-aclapiclient
Version: 0.1.6
Summary: Python ACL API client
Home-page: http://ngit.globoi.com/python-aclapi/python-aclapi
Author: Time Storm
Author-email: storm@corp.globo.com
License: UNKNOWN
Platform: UNKNOWN
Classifier: Development Status :: 4 - Beta
Classifier: Operating System :: POSIX :: Linux
Classifier: Programming Language :: Python :: 2.7
Classifier: Environment :: No Input/Output (Daemon)
